scripts/__init__.py
scripts/__main__.py
scripts/bitbucket/__init__.py
scripts/bitbucket/bulk_update/.env.template
scripts/bitbucket/bulk_update/README.md
scripts/bitbucket/bulk_update/__init__.py
scripts/bitbucket/bulk_update/main.py
scripts/bitbucket/bulk_update/repositories.txt
scripts/bitbucket/bulk_update/requirements.txt
scripts/bitbucket/bulk_update/stats.csv
scripts/bitbucket/bulk_update/tvav-repositories.txt
scripts/bitbucket/bulk_update/update_methods.py
scripts/bitbucket/deploy/.env.template
scripts/bitbucket/deploy/IMPROVEMENTS.md
scripts/bitbucket/deploy/README.md
scripts/bitbucket/deploy/__init__.py
scripts/bitbucket/deploy/main.py
scripts/bitbucket/deploy/requirements.txt
scripts/bitbucket/deploy/stats.csv
scripts/eurosport/__init__.py
scripts/eurosport/fix_eurosport_epg/.env
scripts/eurosport/fix_eurosport_epg/README.md
scripts/eurosport/fix_eurosport_epg/__init__.py
scripts/eurosport/fix_eurosport_epg/fix_epg.py
scripts/eurosport/fix_eurosport_epg/requirements.txt
scripts/eurosport/fix_eurosport_epg/test-requirements.txt
scripts/eurosport/generate_dip_reports/.env.template
scripts/eurosport/generate_dip_reports/.gitignore
scripts/eurosport/generate_dip_reports/README.md
scripts/eurosport/generate_dip_reports/__init__.py
scripts/eurosport/generate_dip_reports/main.py
scripts/eurosport/generate_dip_reports/requirements.txt
scripts/eurosport/update_av_work_category/.env.template
scripts/eurosport/update_av_work_category/README.md
scripts/eurosport/update_av_work_category/__init__.py
scripts/eurosport/update_av_work_category/main.py
scripts/eurosport/update_av_work_category/requirements.txt
scripts/generic/__init__.py
scripts/generic/approved_without_timestamp/.env.template
scripts/generic/approved_without_timestamp/.gitignore
scripts/generic/approved_without_timestamp/README.md
scripts/generic/approved_without_timestamp/__init__.py
scripts/generic/approved_without_timestamp/approved_without_timestamp.py
tvav_scripts-0.74.1a2.dist-info/METADATA
tvav_scripts-0.74.1a2.dist-info/WHEEL
tvav_scripts-0.74.1a2.dist-info/entry_points.txt
tvav_scripts-0.74.1a2.dist-info/RECORD
