Metadata-Version: 2.1
Name: tvav-scripts
Version: 0.74.1a2
Summary: Scripts package for TVAV
Home-page: https://bitbucket.org/bmat-music/tvav-scripts/src/master
Author: TVAV-team
Author-email: tvav-sw@bmat.com
Maintainer: TVAV-team
Maintainer-email: tvav-sw@bmat.com
Requires-Python: >=3.9,<4.0.0
Classifier: Programming Language :: Python :: 3
Classifier: Programming Language :: Python :: 3.9
Classifier: Programming Language :: Python :: 3.10
Classifier: Programming Language :: Python :: 3.11
Classifier: Programming Language :: Python :: 3.12
Classifier: Programming Language :: Python :: 3.13
Project-URL: Repository, https://bitbucket.org/bmat-music/tvav-scripts/src/master
